spei/README.md
spei/__init__.py
spei/cep_generator.py
spei/checksum/__init__.py
spei/checksum/factory.py
spei/checksum/generator.py
spei/checksum/types.py
spei/client.py
spei/errors/__init__.py
spei/errors/sice.py
spei/errors/spei.py
spei/exceptions.py
spei/mappings.py
spei/requests/__init__.py
spei/requests/acuse.py
spei/requests/cda.py
spei/requests/orden.py
spei/requests/respuesta.py
spei/resources/__init__.py
spei/resources/acuse.py
spei/resources/cda.py
spei/resources/ensesion.py
spei/resources/mensaje.py
spei/resources/orden.py
spei/resources/payments.py
spei/resources/respuesta.py
spei/resources/validators.py
spei/responses/__init__.py
spei/responses/orden.py
spei/responses/respuesta.py
spei/sice.py
spei/signature/__init__.py
spei/signature/factory.py
spei/signature/payload.py
spei/signature/types.py
spei/types/__init__.py
spei/types/common.py
spei/types/sice.py
spei/types/spei.py
spei/utils.py
spei_python-1.0.8.dist-info/METADATA
spei_python-1.0.8.dist-info/WHEEL
spei_python-1.0.8.dist-info/RECORD
