Metadata-Version: 2.4
Name: spei-python
Version: 1.0.8
Summary: 
Author: tech
Author-email: tech@fondeadora.com
Requires-Python: >=3.11,<4.0
Classifier: Programming Language :: Python :: 3
Classifier: Programming Language :: Python :: 3.11
Classifier: Programming Language :: Python :: 3.12
Classifier: Programming Language :: Python :: 3.13
Classifier: Programming Language :: Python :: 3.14
Requires-Dist: cryptography (>=3.0,<44.1)
Requires-Dist: lxml (>=5.0.0,<6.0.0)
Requires-Dist: pydantic (>=1.10.17,<3)
Requires-Dist: requests (>=2.32.2,<3.0.0)
Requires-Dist: unidecode (>=1.3.8,<2.0.0)
